.DS_Store
BlizzPy-1.0.3.dist-info/DESCRIPTION.rst
BlizzPy-1.0.3.dist-info/METADATA
BlizzPy-1.0.3.dist-info/RECORD
BlizzPy-1.0.3.dist-info/WHEEL
BlizzPy-1.0.3.dist-info/metadata.json
BlizzPy-1.0.3.dist-info/top_level.txt
blizzpy/d3.py
blizzpy/sc2.py
blizzpy/wow.py
