Metadata-Version: 2.0
Name: BlizzPy
Version: 1.0.3
Summary: A comprehensive open-source API wrapper library for Blizzard's REST API. Currently supports WoW, SC2, and Diablo 3 game data.
Home-page: https://github.com/lounotlew/BlizzPy
Author: Lewis Kim
Author-email: lewis.k@berkeley.edu
License: Apache2
Platform: UNKNOWN
Classifier: Development Status :: 4 - Beta
Classifier: Intended Audience :: Developers
Classifier: License :: OSI Approved :: Apache Software License
Classifier: Programming Language :: Python :: 3
Requires-Python: >=3.6
Requires-Dist: pandas (>=0.23.0)
Requires-Dist: requests (>=2.18.4requests-oauthlib>=1.0.0)
Requires-Dist: requests-toolbelt (>=0.8.0)
